{
  "$schema": "https://raw.githubusercontent.com/earendil-works/pi-mono/main/packages/coding-agent/src/modes/interactive/theme/theme-schema.json",
  "name": "senzu",
  "vars": {
    "foreground": "#e8e8d3",
    "background": "#151515",
    "grey": "#888888",
    "greyOne": "#1c1c1c",
    "greyTwo": "#f0f0f0",
    "greyThree": "#333333",
    "regentGrey": "#9098A0",
    "scorpion": "#606060",
    "codGrey": "#101010",
    "tundora": "#404040",
    "zambezi": "#605958",
    "silverRust": "#ccc5c4",
    "silver": "#c7c7c7",
    "alto": "#dddddd",
    "gravel": "#403c41",
    "boulder": "#777777",
    "cocoaBrown": "#302028",
    "greyChateau": "#a0a8b0",
    "brightGrey": "#384048",
    "shuttleGrey": "#535d66",
    "mineShaft": "#1f1f1f",
    "temptress": "#40000a",
    "bayouxBlue": "#556779",
    "totalWhite": "#ffffff",
    "totalBlack": "#000000",
    "cadetBlue": "#b0b8c0",
    "perano": "#b0d0f0",
    "wewak": "#cc88a3",
    "mantis": "#70b950",
    "rawSienna": "#d98870",
    "highland": "#799d6a",
    "hoki": "#668799",
    "greenSmoke": "#99ad6a",
    "costaDelSol": "#556633",
    "bilobaFlower": "#c6b6ee",
    "morningGlory": "#8fbfdc",
    "goldenrod": "#fad07a",
    "shipCove": "#8197bf",
    "koromiko": "#e6a75a",
    "brandy": "#dad085",
    "oldBrick": "#902020",
    "darkBlue": "#0000df",
    "ripePlum": "#540063",
    "casal": "#2D7067",
    "purple": "#700089",
    "teaGreen": "#d2ebbe",
    "dell": "#437019",
    "calypso": "#2B5B77",
    "error": "#d74545",
    "warning": "#ffaf00",
    "info": "#5f9ecf",
    "hint": "#a08070",
    "ok": "#afd787"
  },
  "colors": {
    "accent": "morningGlory",
    "border": "tundora",
    "borderAccent": "greenSmoke",
    "borderMuted": "greyThree",
    "success": "ok",
    "error": "error",
    "warning": "warning",
    "muted": "greyChateau",
    "dim": "scorpion",
    "text": "foreground",
    "thinkingText": "regentGrey",
    "selectedBg": "greyOne",
    "userMessageBg": "greyThree",
    "userMessageText": "foreground",
    "customMessageBg": "gravel",
    "customMessageText": "foreground",
    "customMessageLabel": "greenSmoke",
    "toolPendingBg": "mineShaft",
    "toolSuccessBg": "gravel",
    "toolErrorBg": "temptress",
    "toolTitle": "morningGlory",
    "toolOutput": "foreground",
    "mdHeading": "greenSmoke",
    "mdLink": "morningGlory",
    "mdLinkUrl": "regentGrey",
    "mdCode": "silver",
    "mdCodeBlock": "foreground",
    "mdCodeBlockBorder": "boulder",
    "mdQuote": "greyChateau",
    "mdQuoteBorder": "boulder",
    "mdHr": "boulder",
    "mdListBullet": "morningGlory",
    "toolDiffAdded": "ok",
    "toolDiffRemoved": "error",
    "toolDiffContext": "greyChateau",
    "syntaxComment": "grey",
    "syntaxKeyword": "shipCove",
    "syntaxFunction": "goldenrod",
    "syntaxVariable": "foreground",
    "syntaxString": "greenSmoke",
    "syntaxNumber": "rawSienna",
    "syntaxType": "koromiko",
    "syntaxOperator": "boulder",
    "syntaxPunctuation": "silver",
    "thinkingOff": "greyThree",
    "thinkingMinimal": "boulder",
    "thinkingLow": "greyChateau",
    "thinkingMedium": "greenSmoke",
    "thinkingHigh": "morningGlory",
    "thinkingXhigh": "warning",
    "bashMode": "warning"
  },
  "export": {
    "pageBg": "background",
    "cardBg": "greyOne",
    "infoBg": "mineShaft"
  }
}
